parsel_tongue/__init__.py
parsel_tongue/evaluator.py
parsel_tongue/exceptions.py
parsel_tongue/lexer.py
parsel_tongue/main.py
parsel_tongue/parser.py
viper_script-0.0.2.dist-info/METADATA
viper_script-0.0.2.dist-info/WHEEL
viper_script-0.0.2.dist-info/entry_points.txt
viper_script-0.0.2.dist-info/top_level.txt
viper_script-0.0.2.dist-info/RECORD
