Metadata-Version: 2.1
Name: viper_script
Version: 0.0.2
Summary: A New Fun experience
Home-page: https://github.com/yuvraj-dhiman/T.U.R.B.O
Author: Yuvraj Dhiman
Author-email: yuvraj.dhiman2003@gmail.com
Classifier: Programming Language :: Python :: 3
Classifier: License :: OSI Approved :: MIT License
Classifier: Operating System :: OS Independent
Requires-Python: >=3.6
